{
    "Name": "Village",
    "Description": "Village",
    "Sprite": {
        "FilePath": "building/village.png"
    },
    "Tags": [
        "Building"
    ],
    "Defence": {
        "DefenceIndicator": "MEDIUM",
        "SpecificDefence": [
            {
                "Defence": 0.2,
                "ApplyToEnemies": false
            }
        ]
    },
    "Capture": {
        "PointsToCapture": 2
    },
    "Money": {
        "PrimaryIncome": 4,
        "SecondaryIncome": 4,
        "TertiaryIncome": 4
    },
    "Purchase": {
        "Selector": {
            "AllowEntities": [
                "Archer",
                "Barbarian",
                "Knight",
                "Rouge",
                "Warrior"
            ]
        },
        "AbilityConfig": {
            "PointCost": 1,
            "EndsTurn": true
        },
        "EntitiesProducedHaveActions": false
    }
}